zabgrab/__init__.py
zabgrab/__main__.py
zabgrab/_version.py
zabgrab/utilities.py
zabgrab-0.1.2.dist-info/LICENSE
zabgrab-0.1.2.dist-info/METADATA
zabgrab-0.1.2.dist-info/WHEEL
zabgrab-0.1.2.dist-info/entry_points.txt
zabgrab-0.1.2.dist-info/top_level.txt
zabgrab-0.1.2.dist-info/RECORD
