Metadata-Version: 2.1
Name: zabgrab
Version: 0.1.2
Summary: Zabbix data retrieval
Author-email: Sean Leavey <sean.leavey@stfc.ac.uk>
License: GPL-3.0-or-later
Project-URL: Source Code, https://gitlab.stfc.ac.uk/lisa/lab/zabgrab
Classifier: Development Status :: 3 - Alpha
Classifier: License :: OSI Approved :: GNU General Public License v3 or later (GPLv3+)
Classifier: Natural Language :: English
Classifier: Operating System :: OS Independent
Classifier: Programming Language :: Python :: 3
Classifier: Programming Language :: Python :: 3.8
Classifier: Programming Language :: Python :: 3.9
Classifier: Programming Language :: Python :: 3.10
Classifier: Programming Language :: Python :: 3.11
Requires-Python: >=3.8
License-File: LICENSE
Requires-Dist: click >=8.0.0
Requires-Dist: dateparser >=1.1.7
Requires-Dist: tomli >=2.0.0
Requires-Dist: pyzabbix >=1.2.1
Requires-Dist: numpy >=1.20
Requires-Dist: scipy >=1.6
Provides-Extra: dev
Requires-Dist: black ; extra == 'dev'
Requires-Dist: pre-commit ; extra == 'dev'
Requires-Dist: flake8 ; extra == 'dev'
